Workbook

Sheet LBO
A1: Leveraged buyout model: Dropbox
A2: Hypothetical transaction at 31 December 2025. USD millions, except per-share data. Blue figures are inputs; black figures are formulas.
A4: Transaction assumptions
A5: Share price, 31 Dec 2025 (USD) | B5: 27.799999 | C5: Yahoo Finance closing price
A6: Acquisition premium | B6: 0.3 | C6: Assumption
A7: Offer price per share (USD) | B7: =B5*(1+B6) -> 36.139999
A8: Diluted shares (millions) | B8: 272.8 | C8: Form 10-K, weighted average for 2025
A9: Equity purchase price | B9: =B7*B8 -> 9858.9917
A10: Existing debt, refinanced | B10: 2819 | C10: Form 10-K: convertible notes and credit facility; excludes leases
A11: Existing cash and short-term investments | B11: 1038.2 | C11: Form 10-K
A12: Enterprise value | B12: =B9+B10-B11 -> 11639.792
A13: EBITDA, 2025 | B13: =C44 -> 846.6
A14: Entry EV / EBITDA | B14: =B12/B13 -> 13.748868
A15: Transaction fees, % of enterprise value | B15: 0.02 | C15: Assumption
A16: Minimum cash kept in the company | B16: 200 | C16: Assumption
A17: Term loan, x EBITDA | B17: 4.5 | C17: Assumption
A18: Term loan interest rate | B18: 0.085 | C18: Assumption
A19: Senior notes, x EBITDA | B19: 1.5 | C19: Assumption
A20: Senior notes interest rate | B20: 0.105 | C20: Assumption
A21: Tax rate | B21: 0.21 | C21: US federal statutory rate
A22: Exit EV / EBITDA | B22: =B14 -> 13.748868 | C22: Set equal to the entry multiple
A24: Sources and uses
A25: Uses
A26: Purchase of equity | B26: =B9 -> 9858.9917
A27: Refinancing of existing debt | B27: =B10 -> 2819
A28: Transaction fees | B28: =B12*B15 -> 232.79583
A29: Total uses | B29: =SUM(B26:B28) -> 12910.788
A31: Sources
A32: Term loan | B32: =B17*B13 -> 3809.7
A33: Senior notes | B33: =B19*B13 -> 1269.9
A34: Cash from the company's balance sheet | B34: =B11-B16 -> 838.2
A35: Sponsor equity | B35: =B29-B32-B33-B34 -> 6992.9876
A36: Total sources | B36: =SUM(B32:B35) -> 12910.788
A37: Sponsor equity, % of total sources | B37: =B35/B36 -> 0.54163912
A38: Total debt / EBITDA at entry | B38: =(B32+B33)/B13 -> 6
B40: Historical | C40: Historical | D40: Projected | E40: Projected | F40: Projected | G40: Projected | H40: Projected
A41: Fiscal year ended 31 December | B41: 2024 | C41: 2025 | D41: 2026 | E41: 2027 | F41: 2028 | G41: 2029 | H41: 2030
A42: Revenue | B42: 2548.2 | C42: 2521 | D42: =C42*(1+D43) -> 2521 | E42: =D42*(1+E43) -> 2546.21 | F42: =E42*(1+F43) -> 2571.6721 | G42: =F42*(1+G43) -> 2623.1055 | H42: =G42*(1+H43) -> 2675.5677
A43: % growth | C43: =C42/B42-1 -> -0.010674201 | D43: 0 | E43: 0.01 | F43: 0.01 | G43: 0.02 | H43: 0.02
A44: EBITDA | B44: 623.3 | C44: 846.6 | D44: =D42*D45 -> 907.56 | E44: =E42*E45 -> 967.5598 | F44: =F42*F45 -> 1028.6688 | G44: =G42*G45 -> 1075.4733 | H44: =H42*H45 -> 1123.7384
A45: % of sales | B45: =B44/B42 -> 0.24460403 | C45: =C44/C42 -> 0.33581912 | D45: 0.36 | E45: 0.38 | F45: 0.4 | G45: 0.41 | H45: 0.42
A46: D&A | B46: 137.1 | C46: 157.5 | D46: =D42*D47 -> 151.26 | E46: =E42*E47 -> 152.7726 | F46: =F42*F47 -> 154.30033 | G46: =G42*G47 -> 157.38633 | H46: =H42*H47 -> 160.53406
A47: % of sales | B47: =B46/B42 -> 0.053802684 | C47: =C46/C42 -> 0.062475208 | D47: 0.06 | E47: 0.06 | F47: 0.06 | G47: 0.06 | H47: 0.06
A48: EBIT | B48: =B44-B46 -> 486.2 | C48: =C44-C46 -> 689.1 | D48: =D44-D46 -> 756.3 | E48: =E44-E46 -> 814.7872 | F48: =F44-F46 -> 874.36851 | G48: =G44-G46 -> 918.08694 | H48: =H44-H46 -> 963.20436
A49: Interest: term loan | D49: =D61*$B$18 -> 323.8245 | E49: =E61*$B$18 -> 303.73752 | F49: =F61*$B$18 -> 278.37428 | G49: =G61*$B$18 -> 247.30701 | H49: =H61*$B$18 -> 211.21789
A50: Interest: senior notes | D50: =D64*$B$20 -> 133.3395 | E50: =E64*$B$20 -> 133.3395 | F50: =F64*$B$20 -> 133.3395 | G50: =G64*$B$20 -> 133.3395 | H50: =H64*$B$20 -> 133.3395
A51: Pre-tax income | D51: =D48-D49-D50 -> 299.136 | E51: =E48-E49-E50 -> 377.71018 | F51: =F48-F49-F50 -> 462.65474 | G51: =G48-G49-G50 -> 537.44043 | H51: =H48-H49-H50 -> 618.64697
A52: Taxes | D52: =MAX(0,D51*$B$21) -> 62.81856 | E52: =MAX(0,E51*$B$21) -> 79.319138 | F52: =MAX(0,F51*$B$21) -> 97.157494 | G52: =MAX(0,G51*$B$21) -> 112.86249 | H52: =MAX(0,H51*$B$21) -> 129.91586
A53: Net income | D53: =D51-D52 -> 236.31744 | E53: =E51-E52 -> 298.39104 | F53: =F51-F52 -> 365.49724 | G53: =G51-G52 -> 424.57794 | H53: =H51-H52 -> 488.7311
A54: Cash flow
A55: Net income | D55: =D53 -> 236.31744 | E55: =E53 -> 298.39104 | F55: =F53 -> 365.49724 | G55: =G53 -> 424.57794 | H55: =H53 -> 488.7311
A56: Plus: D&A | D56: =D46 -> 151.26 | E56: =E46 -> 152.7726 | F56: =F46 -> 154.30033 | G56: =G46 -> 157.38633 | H56: =H46 -> 160.53406
A57: Less: capital expenditures | D57: =D42*D58 -> 151.26 | E57: =E42*E58 -> 152.7726 | F57: =F42*F58 -> 154.30033 | G57: =G42*G58 -> 157.38633 | H57: =H42*H58 -> 160.53406
A58: % of sales | D58: 0.06 | E58: 0.06 | F58: 0.06 | G58: 0.06 | H58: 0.06
A59: Free cash flow available for debt repayment | D59: =D55+D56-D57 -> 236.31744 | E59: =E55+E56-E57 -> 298.39104 | F59: =F55+F56-F57 -> 365.49724 | G59: =G55+G56-G57 -> 424.57794 | H59: =H55+H56-H57 -> 488.7311
A60: Debt schedule
A61: Term loan: beginning balance | D61: =$B$32 -> 3809.7 | E61: =D63 -> 3573.3826 | F61: =E63 -> 3274.9915 | G61: =F63 -> 2909.4943 | H61: =G63 -> 2484.9163
A62: Repayment (cash sweep) | D62: =MIN(D61,MAX(0,D59)) -> 236.31744 | E62: =MIN(E61,MAX(0,E59)) -> 298.39104 | F62: =MIN(F61,MAX(0,F59)) -> 365.49724 | G62: =MIN(G61,MAX(0,G59)) -> 424.57794 | H62: =MIN(H61,MAX(0,H59)) -> 488.7311
A63: Term loan: ending balance | D63: =D61-D62 -> 3573.3826 | E63: =E61-E62 -> 3274.9915 | F63: =F61-F62 -> 2909.4943 | G63: =G61-G62 -> 2484.9163 | H63: =H61-H62 -> 1996.1852
A64: Senior notes | D64: =$B$33 -> 1269.9 | E64: =$B$33 -> 1269.9 | F64: =$B$33 -> 1269.9 | G64: =$B$33 -> 1269.9 | H64: =$B$33 -> 1269.9
A65: Cash | D65: =$B$16+D59-D62 -> 200 | E65: =D65+E59-E62 -> 200 | F65: =E65+F59-F62 -> 200 | G65: =F65+G59-G62 -> 200 | H65: =G65+H59-H62 -> 200
A66: Total debt | D66: =D63+D64 -> 4843.2826 | E66: =E63+E64 -> 4544.8915 | F66: =F63+F64 -> 4179.3943 | G66: =G63+G64 -> 3754.8163 | H66: =H63+H64 -> 3266.0852
A67: Net debt | D67: =D66-D65 -> 4643.2826 | E67: =E66-E65 -> 4344.8915 | F67: =F66-F65 -> 3979.3943 | G67: =G66-G65 -> 3554.8163 | H67: =H66-H65 -> 3066.0852
A68: Net debt / EBITDA | D68: =D67/D44 -> 5.1162265 | E68: =E67/E44 -> 4.4905664 | F68: =F67/F44 -> 3.8684892 | G68: =G67/G44 -> 3.3053507 | H68: =H67/H44 -> 2.7284688
A70: Returns: exit at the end of 2030
A71: Exit EBITDA, 2030 | B71: =H44 -> 1123.7384
A72: Exit EV / EBITDA | B72: =B22 -> 13.748868
A73: Exit enterprise value | B73: =B71*B72 -> 15450.131
A74: Less: net debt at exit | B74: =H67 -> 3066.0852
A75: Exit equity value | B75: =B73-B74 -> 12384.046
A76: Sponsor equity invested | B76: =B35 -> 6992.9876
A77: Multiple of invested capital (MOIC) | B77: =B75/B76 -> 1.7709235
A78: Internal rate of return (IRR) | B78: =B77^(1/5)-1 -> 0.12108866
A79: Debt repaid over the period | B79: =B32-H63 -> 1813.5148

Sheet Sensitivity
A1: Sensitivity: sponsor IRR to exit multiple and exit year
A2: Rows: exit EV / EBITDA. Columns: year of exit.
A4: Exit multiple \ Exit year | B4: 2028 | C4: 2029 | D4: 2030
A5: =LBO!$B$22+(-2) -> 11.748868 | B5: =((LBO!F44*$A5-LBO!F67)/LBO!$B$35)^(1/3)-1 -> 0.05047723 | C5: =((LBO!G44*$A5-LBO!G67)/LBO!$B$35)^(1/4)-1 -> 0.067493077 | D5: =((LBO!H44*$A5-LBO!H67)/LBO!$B$35)^(1/5)-1 -> 0.077074258
A6: =LBO!$B$22+(-1) -> 12.748868 | B6: =((LBO!F44*$A6-LBO!F67)/LBO!$B$35)^(1/3)-1 -> 0.093154236 | C6: =((LBO!G44*$A6-LBO!G67)/LBO!$B$35)^(1/4)-1 -> 0.097785936 | D6: =((LBO!H44*$A6-LBO!H67)/LBO!$B$35)^(1/5)-1 -> 0.099961538
A7: =LBO!$B$22+(0) -> 13.748868 | B7: =((LBO!F44*$A7-LBO!F67)/LBO!$B$35)^(1/3)-1 -> 0.13273628 | C7: =((LBO!G44*$A7-LBO!G67)/LBO!$B$35)^(1/4)-1 -> 0.12576026 | D7: =((LBO!H44*$A7-LBO!H67)/LBO!$B$35)^(1/5)-1 -> 0.12108866
A8: =LBO!$B$22+(1) -> 14.748868 | B8: =((LBO!F44*$A8-LBO!F67)/LBO!$B$35)^(1/3)-1 -> 0.16972997 | C8: =((LBO!G44*$A8-LBO!G67)/LBO!$B$35)^(1/4)-1 -> 0.15179211 | D8: =((LBO!H44*$A8-LBO!H67)/LBO!$B$35)^(1/5)-1 -> 0.1407337
A9: =LBO!$B$22+(2) -> 15.748868 | B9: =((LBO!F44*$A9-LBO!F67)/LBO!$B$35)^(1/3)-1 -> 0.20452099 | C9: =((LBO!G44*$A9-LBO!G67)/LBO!$B$35)^(1/4)-1 -> 0.17616975 | D9: =((LBO!H44*$A9-LBO!H67)/LBO!$B$35)^(1/5)-1 -> 0.15911187

Sheet Notes
A1: Notes
A2: Method
A3: A financial sponsor buys all the shares at a premium, refinances the existing debt and funds the purchase with new debt and its own equity.
A4: During the holding period, all free cash flow repays the term loan (cash sweep). Interest is calculated on the balance at the beginning of each year.
A5: At exit, the company is sold at an EV / EBITDA multiple. Exit equity value = exit enterprise value - net debt.
A6: MOIC = exit equity value / sponsor equity invested. IRR = MOIC ^ (1 / years) - 1, since there are no interim dividends.
A8: Assumptions
A9: This is a hypothetical transaction built for illustration. It does not describe any real or proposed deal.
A10: The premium, leverage, interest rates, fees, revenue growth, EBITDA margins and capital expenditures are the author's assumptions.
A11: EBITDA is operating income plus depreciation and amortization of intangible assets, after stock-based compensation expense.
A12: Capital expenditures of 6% of sales are meant to cover purchases of equipment and payments on finance leases, which Dropbox uses for its data-center equipment.
A13: Changes in net working capital are assumed to be zero. Lease liabilities are not treated as debt.
... A20: Retrieved on 2026-10-13.
