Workbook

Sheet Multiples
A1: EBITDA multiples: valuing Amazon from US technology comparables
A2: Share prices at 31 December 2025; financials for fiscal year 2025. USD millions unless stated.
A4: Company | B4: Ticker | C4: Role | D4: Market capitalization | E4: Net debt | F4: Enterprise value | G4: EBITDA | H4: EBITDA margin | I4: EV / EBITDA | J4: EV / Revenue
A5: =Inputs!A5 -> Amazon | B5: =Inputs!B5 -> AMZN | C5: =Inputs!C5 -> Target | D5: =Inputs!E5*Inputs!F5 -> 2499088.2 | E5: =Inputs!G5-Inputs!H5 -> -54178 | F5: =D5+E5 -> 2444910.2 | G5: =Inputs!J5+Inputs!K5 -> 145731 | H5: =G5/Inputs!I5 -> 0.20327259 | I5: =F5/G5 -> 16.776871 | J5: =F5/Inputs!I5 -> 3.4102781
A6: =Inputs!A6 -> Microsoft | B6: =Inputs!B6 -> MSFT | C6: =Inputs!C6 -> Comparable | D6: =Inputs!E6*Inputs!F6 -> 3610223.3 | E6: =Inputs!G6-Inputs!H6 -> -51414 | F6: =D6+E6 -> 3558809.3 | G6: =Inputs!J6+Inputs!K6 -> 156528 | H6: =G6/Inputs!I6 -> 0.55560762 | I6: =F6/G6 -> 22.735928 | J6: =F6/Inputs!I6 -> 12.632254
A7: =Inputs!A7 -> Nvidia | B7: =Inputs!B7 -> NVDA | C7: =Inputs!C7 -> Comparable | D7: =Inputs!E7*Inputs!F7 -> 4571861 | E7: =Inputs!G7-Inputs!H7 -> -2137 | F7: =D7+E7 -> 4569724 | G7: =Inputs!J7+Inputs!K7 -> 133230 | H7: =G7/Inputs!I7 -> 0.61698265 | I7: =F7/G7 -> 34.299512 | J7: =F7/Inputs!I7 -> 21.162204
A8: =Inputs!A8 -> Alphabet | B8: =Inputs!B8 -> GOOGL | C8: =Inputs!C8 -> Comparable | D8: =Inputs!E8*Inputs!F8 -> 3827990 | E8: =Inputs!G8-Inputs!H8 -> -78300 | F8: =D8+E8 -> 3749690 | G8: =Inputs!J8+Inputs!K8 -> 150175 | H8: =G8/Inputs!I8 -> 0.37279439 | I8: =F8/G8 -> 24.968803 | J8: =F8/Inputs!I8 -> 9.3082297
A9: =Inputs!A9 -> Meta Platforms | B9: =Inputs!B9 -> META | C9: =Inputs!C9 -> Comparable | D9: =Inputs!E9*Inputs!F9 -> 1699071.7 | E9: =Inputs!G9-Inputs!H9 -> -22848 | F9: =D9+E9 -> 1676223.7 | G9: =Inputs!J9+Inputs!K9 -> 101892 | H9: =G9/Inputs!I9 -> 0.50701114 | I9: =F9/G9 -> 16.450985 | J9: =F9/Inputs!I9 -> 8.3408324
A10: =Inputs!A10 -> Apple | B10: =Inputs!B10 -> AAPL | C10: =Inputs!C10 -> Comparable | D10: =Inputs!E10*Inputs!F10 -> 4079176.7 | E10: =Inputs!G10-Inputs!H10 -> 43960 | F10: =D10+E10 -> 4123136.7 | G10: =Inputs!J10+Inputs!K10 -> 144748 | H10: =G10/Inputs!I10 -> 0.34781731 | I10: =F10/G10 -> 28.48493 | J10: =F10/Inputs!I10 -> 9.9075519
A11: =Inputs!A11 -> Broadcom | B11: =Inputs!B11 -> AVGO | C11: =Inputs!C11 -> Comparable | D11: =Inputs!E11*Inputs!F11 -> 1679623.3 | E11: =Inputs!G11-Inputs!H11 -> 48958 | F11: =D11+E11 -> 1728581.3 | G11: =Inputs!J11+Inputs!K11 -> 34120 | H11: =G11/Inputs!I11 -> 0.53406796 | I11: =F11/G11 -> 50.661821 | J11: =F11/Inputs!I11 -> 27.056856
A12: =Inputs!A12 -> ServiceNow | B12: =Inputs!B12 -> NOW | C12: =Inputs!C12 -> Comparable | D12: =Inputs!E12*Inputs!F12 -> 160342.6 | E12: =Inputs!G12-Inputs!H12 -> -4793 | F12: =D12+E12 -> 155549.6 | G12: =Inputs!J12+Inputs!K12 -> 2562 | H12: =G12/Inputs!I12 -> 0.19295075 | I12: =F12/G12 -> 60.714128 | J12: =F12/Inputs!I12 -> 11.714836
A14: Comparable set (7 companies, Amazon excluded)
A15: Minimum | H15: =MIN(H6:H12) -> 0.19295075 | I15: =MIN(I6:I12) -> 16.450985 | J15: =MIN(J6:J12) -> 8.3408324
A16: Lower quartile | H16: =QUARTILE(H6:H12,1) -> 0.36030585 | I16: =QUARTILE(I6:I12,1) -> 23.852365 | J16: =QUARTILE(J6:J12,1) -> 9.6078908
A17: Median | H17: =MEDIAN(H6:H12) -> 0.50701114 | I17: =MEDIAN(I6:I12) -> 28.48493 | J17: =MEDIAN(J6:J12) -> 11.714836
A18: Upper quartile | H18: =QUARTILE(H6:H12,3) -> 0.54483779 | I18: =QUARTILE(I6:I12,3) -> 42.480667 | J18: =QUARTILE(J6:J12,3) -> 16.897229
A19: Maximum | H19: =MAX(H6:H12) -> 0.61698265 | I19: =MAX(I6:I12) -> 60.714128 | J19: =MAX(J6:J12) -> 27.056856
A20: Average | H20: =AVERAGE(H6:H12) -> 0.4467474 | I20: =AVERAGE(I6:I12) -> 34.045158 | J20: =AVERAGE(J6:J12) -> 14.303252
A22: Implied valuation of Amazon from the comparables' EV / EBITDA
D23: Lower quartile | E23: Median | F23: Upper quartile
A24: EV / EBITDA multiple applied | D24: =I16 -> 23.852365 | E24: =I17 -> 28.48493 | F24: =I18 -> 42.480667
A25: Amazon EBITDA | D25: =G5 -> 145731 | E25: =G5 -> 145731 | F25: =G5 -> 145731
A26: Implied enterprise value | D26: =D24*D25 -> 3476029 | E26: =E24*E25 -> 4151137.4 | F26: =F24*F25 -> 6190750
A27: Less: net debt | D27: =E5 -> -54178 | E27: =E5 -> -54178 | F27: =E5 -> -54178
A28: Implied equity value | D28: =D26-D27 -> 3530207 | E28: =E26-E27 -> 4205315.4 | F28: =F26-F27 -> 6244928
A29: Diluted shares (millions) | D29: =Inputs!F5 -> 10827 | E29: =Inputs!F5 -> 10827 | F29: =Inputs!F5 -> 10827
A30: Implied share price (USD) | D30: =D28*1/D29 -> 326.05588 | E30: =E28*1/E29 -> 388.41003 | F30: =F28*1/F29 -> 576.79209
A31: Actual share price, 31 Dec 2025 (USD) | D31: =Inputs!E5 -> 230.82001 | E31: =Inputs!E5 -> 230.82001 | F31: =Inputs!E5 -> 230.82001
A32: Implied price against actual price | D32: =D30/D31-1 -> 0.41259801 | E32: =E30/E31-1 -> 0.68273987 | F32: =F30/F31-1 -> 1.4988826

Sheet Inputs
A1: Inputs: fiscal year 2025 figures in USD millions, share prices in USD
A2: Blue figures are inputs: reported values from each Form 10-K, and closing share prices on 31 December 2025.
A4: Company | B4: Ticker | C4: Role | D4: Fiscal year end | E4: Share price, 31 Dec 2025 | F4: Diluted shares (millions) | G4: Total debt | H4: Cash and short-term investments | I4: Revenue | J4: Operating income | K4: Depreciation and amortization
A5: Amazon | B5: AMZN | C5: Target | D5: 46022 | E5: 230.82001 | F5: 10827 | G5: 68851 | H5: 123029 | I5: 716924 | J5: 79975 | K5: 65756
A6: Microsoft | B6: MSFT | C6: Comparable | D6: 45838 | E6: 483.62 | F6: 7465 | G6: 43151 | H6: 94565 | I6: 281724 | J6: 128528 | K6: 28000
A7: Nvidia | B7: NVDA | C7: Comparable | D7: 46047 | E7: 186.5 | F7: 24514 | G7: 8468 | H7: 10605 | I7: 215938 | J7: 130387 | K7: 2843
A8: Alphabet | B8: GOOGL | C8: Comparable | D8: 46022 | E8: 313 | F8: 12230 | G8: 48543 | H8: 126843 | I8: 402836 | J8: 129039 | K8: 21136
A9: Meta Platforms | B9: META | C9: Comparable | D9: 46022 | E9: 660.09003 | F9: 2574 | G9: 58744 | H9: 81592 | I9: 200966 | J9: 83276 | K9: 18616
A10: Apple | B10: AAPL | C10: Comparable | D10: 45927 | E10: 271.85999 | F10: 15004.697 | G10: 98657 | H10: 54697 | I10: 416161 | J10: 133050 | K10: 11698
A11: Broadcom | B11: AVGO | C11: Comparable | D11: 45963 | E11: 346.10001 | F11: 4853 | G11: 65136 | H11: 16178 | I11: 63887 | J11: 25484 | K11: 8636
A12: ServiceNow | B12: NOW | C12: Comparable | D12: 46022 | E12: 153.19 | F12: 1046.691 | G12: 1491 | H12: 6284 | I12: 13278 | J12: 1824 | K12: 738

Sheet Notes
A1: Notes
A2: Definitions
A3: Market capitalization = share price x diluted shares.
A4: Net debt = total debt - cash and short-term investments. Enterprise value (EV) = market capitalization + net debt.
A5: EBITDA = operating income + depreciation and amortization.
A6: Implied share price = (comparables' EV / EBITDA x Amazon EBITDA - Amazon net debt) / Amazon diluted shares.
A8: Points to keep in mind
A9: One valuation date, different fiscal years. Prices are closing prices on 31 December 2025. EBITDA is each company's own fiscal year 2025, so it is not a last-twelve-months figure for companies whose year ends before December.
A10: Diluted shares are the weighted average for the fiscal year from the Form 10-K, not the share count on the valuation date.
A11: Total debt excludes lease liabilities. Cash excludes long-term investments, which are large for Apple.
A12: Nvidia: marketable securities are not available under a standard tag in the source, so only cash is deducted and its enterprise value is slightly overstated.
A13: Alphabet: D&A is depreciation of property and equipment only. Microsoft and Broadcom: D&A is depreciation plus amortization of intangible assets from the notes.
... A19: Retrieved on 2026-10-13.
