Workbook

Sheet README
A1: US technology comparable company set: financial statements
A2: Tested party: Amazon. Comparables: Microsoft, Nvidia, Alphabet, Meta Platforms, Apple, Broadcom, ServiceNow.
A4: Source
A5: U.S. SEC EDGAR XBRL 'company facts' data (data.sec.gov). Every reported figure is the value the company tagged in the Form 10-K listed below.
A6: Retrieved on 2026-10-13.
A8: How to read the company sheets
A9: Blue figures are reported values taken from the filing. Black figures are formulas calculated in this workbook.
A10: Column C names the XBRL tag behind each reported line, so any figure can be traced back to the filing.
A11: Lines marked '(residual)' are the difference between a reported total and the lines shown above it. They make each statement add up; they are not figures the company reports.
A12: The statements use one standard layout for all eight companies so they can be compared. They are not copies of each company's own statement layout.
A14: Points to keep in mind
A15: Fiscal years differ. The Summary sheet shows each company's own fiscal year, not calendar 2025. Calendarise before comparing multiples.
... A24: Filings used
A25: Company | B25: Ticker | C25: Fiscal year end | D25: Form 10-K on SEC EDGAR | E25: XBRL data used
A26: Amazon | B26: AMZN | C26: 2025-12-31 | D26: https://www.sec.gov/Archives/edgar/data/1018724/000101872426000004/ | E26: https://data.sec.gov/api/xbrl/companyfacts/CIK0001018724.json
A27: Microsoft | B27: MSFT | C27: 2025-06-30 | D27: https://www.sec.gov/Archives/edgar/data/789019/000095017025100235/ | E27: https://data.sec.gov/api/xbrl/companyfacts/CIK0000789019.json
A28: Nvidia | B28: NVDA | C28: 2026-01-25 | D28: https://www.sec.gov/Archives/edgar/data/1045810/000104581026000021/ | E28: https://data.sec.gov/api/xbrl/companyfacts/CIK0001045810.json
A29: Alphabet | B29: GOOGL | C29: 2025-12-31 | D29: https://www.sec.gov/Archives/edgar/data/1652044/000165204426000018/ | E29: https://data.sec.gov/api/xbrl/companyfacts/CIK0001652044.json
A30: Meta Platforms | B30: META | C30: 2025-12-31 | D30: https://www.sec.gov/Archives/edgar/data/1326801/000162828026003942/ | E30: https://data.sec.gov/api/xbrl/companyfacts/CIK0001326801.json
A31: Apple | B31: AAPL | C31: 2025-09-27 | D31: https://www.sec.gov/Archives/edgar/data/320193/000032019325000079/ | E31: https://data.sec.gov/api/xbrl/companyfacts/CIK0000320193.json
A32: Broadcom | B32: AVGO | C32: 2025-11-02 | D32: https://www.sec.gov/Archives/edgar/data/1730168/000173016825000121/ | E32: https://data.sec.gov/api/xbrl/companyfacts/CIK0001730168.json
A33: ServiceNow | B33: NOW | C33: 2025-12-31 | D33: https://www.sec.gov/Archives/edgar/data/1373715/000137371526000007/ | E33: https://data.sec.gov/api/xbrl/companyfacts/CIK0001373715.json

Sheet Summary
A1: US technology comparable set: fiscal year 2025, USD millions
A3: Ticker | B3: Company | C3: Role | D3: Fiscal year end | E3: Revenue | F3: Gross profit | G3: Operating income | H3: EBITDA | I3: Net income | J3: Gross margin | K3: Operating margin | L3: EBITDA margin | M3: Net margin | N3: Cash and ST investments | O3: Total debt | P3: Total assets | Q3: Total equity
A4: AMZN | B4: Amazon | C4: Tested party | D4: 46022 | E4: =AMZN!B6 -> 716924 | F4: =AMZN!B8 -> 360510 | G4: =AMZN!B15 -> 79975 | H4: =AMZN!B31 -> 145731 | I4: =AMZN!B22 -> 77670 | J4: =AMZN!B8/AMZN!B6 -> 0.50285665 | K4: =AMZN!B15/AMZN!B6 -> 0.11155297 | L4: =AMZN!B31/AMZN!B6 -> 0.20327259 | M4: =AMZN!B22/AMZN!B6 -> 0.10833784 | N4: =AMZN!B59 -> 123029 | O4: =AMZN!B58 -> 68851 | P4: =AMZN!B45 -> 818042 | Q4: =AMZN!B54 -> 411065
A5: MSFT | B5: Microsoft | C5: Comparable | D5: 45838 | E5: =MSFT!B6 -> 281724 | F5: =MSFT!B8 -> 193893 | G5: =MSFT!B15 -> 128528 | H5: =MSFT!B31 -> 156528 | I5: =MSFT!B22 -> 101832 | J5: =MSFT!B8/MSFT!B6 -> 0.68823742 | K5: =MSFT!B15/MSFT!B6 -> 0.45621956 | L5: =MSFT!B31/MSFT!B6 -> 0.55560762 | M5: =MSFT!B22/MSFT!B6 -> 0.36146015 | N5: =MSFT!B59 -> 94565 | O5: =MSFT!B58 -> 43151 | P5: =MSFT!B45 -> 619003 | Q5: =MSFT!B54 -> 343479
A6: NVDA | B6: Nvidia | C6: Comparable | D6: 46047 | E6: =NVDA!B6 -> 215938 | F6: =NVDA!B8 -> 153463 | G6: =NVDA!B15 -> 130387 | H6: =NVDA!B31 -> 133230 | I6: =NVDA!B22 -> 120067 | J6: =NVDA!B8/NVDA!B6 -> 0.71068084 | K6: =NVDA!B15/NVDA!B6 -> 0.60381684 | L6: =NVDA!B31/NVDA!B6 -> 0.61698265 | M6: =NVDA!B22/NVDA!B6 -> 0.55602534 | N6: =NVDA!B59 -> 10605 | O6: =NVDA!B58 -> 8468 | P6: =NVDA!B45 -> 206803 | Q6: =NVDA!B54 -> 157293
A7: GOOGL | B7: Alphabet | C7: Comparable | D7: 46022 | E7: =GOOGL!B6 -> 402836 | F7: =GOOGL!B8 -> 240301 | G7: =GOOGL!B15 -> 129039 | H7: =GOOGL!B31 -> 150175 | I7: =GOOGL!B22 -> 132170 | J7: =GOOGL!B8/GOOGL!B6 -> 0.59652315 | K7: =GOOGL!B15/GOOGL!B6 -> 0.32032639 | L7: =GOOGL!B31/GOOGL!B6 -> 0.37279439 | M7: =GOOGL!B22/GOOGL!B6 -> 0.32809878 | N7: =GOOGL!B59 -> 126843 | O7: =GOOGL!B58 -> 48543 | P7: =GOOGL!B45 -> 595281 | Q7: =GOOGL!B54 -> 415265
A8: META | B8: Meta Platforms | C8: Comparable | D8: 46022 | E8: =META!B6 -> 200966 | F8: =META!B8 -> 164791 | G8: =META!B15 -> 83276 | H8: =META!B31 -> 101892 | I8: =META!B22 -> 60458 | J8: =META!B8/META!B6 -> 0.81999443 | K8: =META!B15/META!B6 -> 0.41437855 | L8: =META!B31/META!B6 -> 0.50701114 | M8: =META!B22/META!B6 -> 0.30083696 | N8: =META!B59 -> 81592 | O8: =META!B58 -> 58744 | P8: =META!B45 -> 366021 | Q8: =META!B54 -> 217243
A9: AAPL | B9: Apple | C9: Comparable | D9: 45927 | E9: =AAPL!B6 -> 416161 | F9: =AAPL!B8 -> 195201 | G9: =AAPL!B15 -> 133050 | H9: =AAPL!B31 -> 144748 | I9: =AAPL!B22 -> 112010 | J9: =AAPL!B8/AAPL!B6 -> 0.46905164 | K9: =AAPL!B15/AAPL!B6 -> 0.319708 | L9: =AAPL!B31/AAPL!B6 -> 0.34781731 | M9: =AAPL!B22/AAPL!B6 -> 0.26915064 | N9: =AAPL!B59 -> 54697 | O9: =AAPL!B58 -> 98657 | P9: =AAPL!B45 -> 359241 | Q9: =AAPL!B54 -> 73733
A10: AVGO | B10: Broadcom | C10: Comparable | D10: 45963 | E10: =AVGO!B6 -> 63887 | F10: =AVGO!B8 -> 43294 | G10: =AVGO!B15 -> 25484 | H10: =AVGO!B31 -> 34120 | I10: =AVGO!B22 -> 23126 | J10: =AVGO!B8/AVGO!B6 -> 0.67766525 | K10: =AVGO!B15/AVGO!B6 -> 0.39889179 | L10: =AVGO!B31/AVGO!B6 -> 0.53406796 | M10: =AVGO!B22/AVGO!B6 -> 0.36198288 | N10: =AVGO!B59 -> 16178 | O10: =AVGO!B58 -> 65136 | P10: =AVGO!B45 -> 171092 | Q10: =AVGO!B54 -> 81292
A11: NOW | B11: ServiceNow | C11: Comparable | D11: 46022 | E11: =NOW!B6 -> 13278 | F11: =NOW!B8 -> 10295 | G11: =NOW!B15 -> 1824 | H11: =NOW!B31 -> 2562 | I11: =NOW!B22 -> 1748 | J11: =NOW!B8/NOW!B6 -> 0.77534267 | K11: =NOW!B15/NOW!B6 -> 0.13737009 | L11: =NOW!B31/NOW!B6 -> 0.19295075 | M11: =NOW!B22/NOW!B6 -> 0.13164633 | N11: =NOW!B59 -> 6284 | O11: =NOW!B58 -> 1491 | P11: =NOW!B45 -> 26038 | Q11: =NOW!B54 -> 12964

Sheet AMZN
A1: Amazon (AMZN)
A2: Form 10-K, accession 0001018724-26-000004. USD millions, except per-share data; shares in millions.
A4: Fiscal year ended | B4: 2025-12-31 | C4: Source (us-gaap XBRL tag)
A5: INCOME STATEMENT
A6: Revenue | B6: 716924 | C6: RevenueFromContractWithCustomerExcludingAssessedTax
A7: Cost of revenue | B7: 356414 | C7: CostOfGoodsAndServicesSold
A8: Gross profit | B8: =B6-B7 -> 360510 | C8: Calculated
A9: Research and development | C9: Not reported under a standard tag
A10: Selling, general and administrative | B10: =B11+B12 -> 58301 | C10: Calculated
A11: of which: sales and marketing | B11: 47129 | C11: MarketingExpense
A12: of which: general and administrative | B12: 11172 | C12: GeneralAndAdministrativeExpense
A13: Other operating expenses, net (residual) | B13: =B6-B7-B9-B10-B15 -> 222234 | C13: Calculated
A14: Total costs and expenses | B14: =B6-B15 -> 636949 | C14: Calculated
A15: Operating income | B15: 79975 | C15: OperatingIncomeLoss
A16: Non-operating income (expense), net | B16: =B19-B15 -> 17336 | C16: Calculated
A17: of which: interest and investment income | B17: 4381 | C17: InvestmentIncomeInterest
A18: of which: interest expense | B18: 2274 | C18: InterestExpenseNonoperating
A19: Income before income taxes | B19: 97311 | C19: IncomeLossFromContinuingOperationsBeforeIncomeTaxesMinorityInterestAndIncomeLossFromEquityMethodInvestments
A20: Provision for income taxes | B20: 19087 | C20: IncomeTaxExpenseBenefit
A21: Equity-method, discontinued operations and other, net | B21: =B22-B19+B20 -> -554 | C21: Calculated
A22: Net income | B22: 77670 | C22: NetIncomeLoss
A23: EPS, basic (USD) | B23: 7.29 | C23: EarningsPerShareBasic
A24: EPS, diluted (USD) | B24: 7.17 | C24: EarningsPerShareDiluted
A25: Weighted average shares, basic | B25: 10656 | C25: WeightedAverageNumberOfSharesOutstandingBasic
A26: Weighted average shares, diluted | B26: 10827 | C26: WeightedAverageNumberOfDilutedSharesOutstanding
A27: Memo
A28: Depreciation and amortization | B28: 65756 | C28: DepreciationDepletionAndAmortization
A29: Amortization of intangible assets | B29: 817 | C29: AmortizationOfIntangibleAssets
A30: Stock-based compensation | B30: 19467 | C30: ShareBasedCompensation
A31: EBITDA (operating income + D&A) | B31: =B15+B28 -> 145731 | C31: Calculated
A33: BALANCE SHEET
A34: Cash and cash equivalents | B34: 86810 | C34: CashAndCashEquivalentsAtCarryingValue
A35: Short-term investments / marketable securities | B35: 36219 | C35: MarketableSecuritiesCurrent
A36: Accounts receivable, net | B36: 67729 | C36: AccountsReceivableNetCurrent
A37: Inventories | B37: 38325 | C37: InventoryNet
A38: Other current assets (residual) | B38: =B39-B34-B35-B36-B37 -> 0 | C38: Calculated
A39: Total current assets | B39: 229083 | C39: AssetsCurrent
A40: Property and equipment, net | B40: 357025 | C40: PropertyPlantAndEquipmentNet
A41: Operating lease right-of-use assets | B41: 86054 | C41: OperatingLeaseRightOfUseAsset
A42: Goodwill | B42: 23273 | C42: Goodwill
A43: Intangible assets, net | B43: 9197 | C43: IntangibleAssetsNetExcludingGoodwill
A44: Other non-current assets (residual) | B44: =B45-B39-B40-B41-B42-B43 -> 113410 | C44: Calculated
A45: Total assets | B45: 818042 | C45: Assets
A46: Accounts payable | B46: 121909 | C46: AccountsPayableCurrent
A47: Deferred / unearned revenue, current | B47: 20576 | C47: ContractWithCustomerLiabilityCurrent
A48: Short-term debt and current portion of long-term debt | B48: 3203 | C48: LongTermDebtCurrent + ShortTermBorrowings
A49: Other current liabilities (residual) | B49: =B50-B46-B47-B48 -> 72317 | C49: Calculated
A50: Total current liabilities | B50: 218005 | C50: LiabilitiesCurrent
A51: Long-term debt | B51: 65648 | C51: LongTermDebtNoncurrent
A52: Other non-current liabilities (residual) | B52: =B53-B50-B51 -> 123324 | C52: Calculated
A53: Total liabilities | B53: =B55-B54 -> 406977 | C53: Calculated
A54: Total stockholders' equity | B54: 411065 | C54: StockholdersEquity
A55: Total liabilities and equity | B55: 818042 | C55: LiabilitiesAndStockholdersEquity
A56: Check: assets - liabilities and equity | B56: =B45-B55 -> 0 | C56: Calculated
A57: Memo
A58: Total debt (excl. leases) | B58: =B48+B51 -> 68851 | C58: Calculated
A59: Cash and short-term investments | B59: =B34+B35 -> 123029 | C59: Calculated
A60: Net debt | B60: =B58-B59 -> -54178 | C60: Calculated
A61: Common shares outstanding | B61: 10731 | C61: CommonStockSharesOutstanding
A63: CASH FLOW STATEMENT
A64: Net income | B64: =B22 -> 77670 | C64: Calculated
A65: Depreciation and amortization | B65: =B28 -> 65756 | C65: Calculated
A66: Stock-based compensation | B66: =B30 -> 19467 | C66: Calculated
A67: Other adjustments and working capital (residual) | B67: =B68-B64-B65-B66 -> -23379 | C67: Calculated
A68: Net cash from operating activities | B68: 139514 | C68: NetCashProvidedByUsedInOperatingActivities
A69: Capital expenditures | B69: -131819 | C69: PaymentsToAcquireProductiveAssets
A70: Other investing activities (residual) | B70: =B71-B69 -> -10726 | C70: Calculated
A71: Net cash from investing activities | B71: -142545 | C71: NetCashProvidedByUsedInInvestingActivities
A72: Repurchases of common stock | C72: Not reported under a standard tag
A73: Dividends paid | C73: Not reported under a standard tag
A74: Other financing activities (residual) | B74: =B75-B72-B73 -> 9661 | C74: Calculated
A75: Net cash from financing activities | B75: 9661 | C75: NetCashProvidedByUsedInFinancingActivities
A76: Effect of exchange rates on cash | B76: 1164 | C76: EffectOfExchangeRateOnCashCashEquivalentsRestrictedCashAndRestrictedCashEquivalentsIncludingDisposalGroupAndDiscontinuedOperations
A77: Net change in cash | B77: =B68+B71+B75+B76 -> 7794 | C77: Calculated
A78: Memo
A79: Free cash flow (operating cash flow - capex) | B79: =B68+B69 -> 7695 | C79: Calculated

Sheet MSFT
A1: Microsoft (MSFT)
A2: Form 10-K, accession 0000950170-25-100235. USD millions, except per-share data; shares in millions.
A4: Fiscal year ended | B4: 2025-06-30 | C4: Source (us-gaap XBRL tag)
A5: INCOME STATEMENT
A6: Revenue | B6: 281724 | C6: RevenueFromContractWithCustomerExcludingAssessedTax
A7: Cost of revenue | B7: 87831 | C7: CostOfGoodsAndServicesSold
A8: Gross profit | B8: 193893 | C8: GrossProfit
A9: Research and development | B9: 32488 | C9: ResearchAndDevelopmentExpense
A10: Selling, general and administrative | B10: =B11+B12 -> 32877 | C10: Calculated
A11: of which: sales and marketing | B11: 25654 | C11: SellingAndMarketingExpense
A12: of which: general and administrative | B12: 7223 | C12: GeneralAndAdministrativeExpense
A13: Other operating expenses, net (residual) | B13: =B6-B7-B9-B10-B15 -> 0 | C13: Calculated
A14: Total costs and expenses | B14: =B6-B15 -> 153196 | C14: Calculated
A15: Operating income | B15: 128528 | C15: OperatingIncomeLoss
A16: Non-operating income (expense), net | B16: =B19-B15 -> -4901 | C16: Calculated
A17: of which: interest and investment income | B17: 2647 | C17: InvestmentIncomeNet
A18: of which: interest expense | B18: 2385 | C18: InterestExpenseNonoperating
A19: Income before income taxes | B19: 123627 | C19: IncomeLossFromContinuingOperationsBeforeIncomeTaxesExtraordinaryItemsNoncontrollingInterest
A20: Provision for income taxes | B20: 21795 | C20: IncomeTaxExpenseBenefit
A21: Equity-method, discontinued operations and other, net | B21: =B22-B19+B20 -> 0 | C21: Calculated
A22: Net income | B22: 101832 | C22: NetIncomeLoss
A23: EPS, basic (USD) | B23: 13.7 | C23: EarningsPerShareBasic
A24: EPS, diluted (USD) | B24: 13.64 | C24: EarningsPerShareDiluted
A25: Weighted average shares, basic | B25: 7433 | C25: WeightedAverageNumberOfSharesOutstandingBasic
A26: Weighted average shares, diluted | B26: 7465 | C26: WeightedAverageNumberOfDilutedSharesOutstanding
A27: Memo
A28: Depreciation and amortization | B28: 28000 | C28: Depreciation + AmortizationOfIntangibleAssets
A29: Amortization of intangible assets | B29: 6000 | C29: AmortizationOfIntangibleAssets
A30: Stock-based compensation | B30: 11974 | C30: ShareBasedCompensation
A31: EBITDA (operating income + D&A) | B31: =B15+B28 -> 156528 | C31: Calculated
A33: BALANCE SHEET
A34: Cash and cash equivalents | B34: 30242 | C34: CashAndCashEquivalentsAtCarryingValue
A35: Short-term investments / marketable securities | B35: 64323 | C35: ShortTermInvestments
A36: Accounts receivable, net | B36: 69905 | C36: AccountsReceivableNetCurrent
A37: Inventories | B37: 938 | C37: InventoryNet
A38: Other current assets (residual) | B38: =B39-B34-B35-B36-B37 -> 25723 | C38: Calculated
A39: Total current assets | B39: 191131 | C39: AssetsCurrent
A40: Property and equipment, net | B40: 204966 | C40: PropertyPlantAndEquipmentNet
A41: Operating lease right-of-use assets | B41: 24823 | C41: OperatingLeaseRightOfUseAsset
A42: Goodwill | B42: 119509 | C42: Goodwill
A43: Intangible assets, net | B43: 22604 | C43: FiniteLivedIntangibleAssetsNet
A44: Other non-current assets (residual) | B44: =B45-B39-B40-B41-B42-B43 -> 55970 | C44: Calculated
A45: Total assets | B45: 619003 | C45: Assets
A46: Accounts payable | B46: 27724 | C46: AccountsPayableCurrent
A47: Deferred / unearned revenue, current | B47: 64555 | C47: ContractWithCustomerLiabilityCurrent
A48: Short-term debt and current portion of long-term debt | B48: 2999 | C48: LongTermDebtCurrent + CommercialPaper
A49: Other current liabilities (residual) | B49: =B50-B46-B47-B48 -> 45940 | C49: Calculated
A50: Total current liabilities | B50: 141218 | C50: LiabilitiesCurrent
A51: Long-term debt | B51: 40152 | C51: LongTermDebtNoncurrent
A52: Other non-current liabilities (residual) | B52: =B53-B50-B51 -> 94154 | C52: Calculated
A53: Total liabilities | B53: 275524 | C53: Liabilities
A54: Total stockholders' equity | B54: 343479 | C54: StockholdersEquity
A55: Total liabilities and equity | B55: 619003 | C55: LiabilitiesAndStockholdersEquity
A56: Check: assets - liabilities and equity | B56: =B45-B55 -> 0 | C56: Calculated
A57: Memo
A58: Total debt (excl. leases) | B58: =B48+B51 -> 43151 | C58: Calculated
A59: Cash and short-term investments | B59: =B34+B35 -> 94565 | C59: Calculated
A60: Net debt | B60: =B58-B59 -> -51414 | C60: Calculated
A61: Common shares outstanding | B61: 7434 | C61: CommonStockSharesOutstanding
A63: CASH FLOW STATEMENT
A64: Net income | B64: =B22 -> 101832 | C64: Calculated
A65: Depreciation and amortization | B65: =B28 -> 28000 | C65: Calculated
A66: Stock-based compensation | B66: =B30 -> 11974 | C66: Calculated
A67: Other adjustments and working capital (residual) | B67: =B68-B64-B65-B66 -> -5644 | C67: Calculated
A68: Net cash from operating activities | B68: 136162 | C68: NetCashProvidedByUsedInOperatingActivities
A69: Capital expenditures | B69: -64551 | C69: PaymentsToAcquirePropertyPlantAndEquipment
A70: Other investing activities (residual) | B70: =B71-B69 -> -8048 | C70: Calculated
A71: Net cash from investing activities | B71: -72599 | C71: NetCashProvidedByUsedInInvestingActivities
A72: Repurchases of common stock | B72: -18420 | C72: PaymentsForRepurchaseOfCommonStock
A73: Dividends paid | B73: -24082 | C73: PaymentsOfDividendsCommonStock
A74: Other financing activities (residual) | B74: =B75-B72-B73 -> -9197 | C74: Calculated
A75: Net cash from financing activities | B75: -51699 | C75: NetCashProvidedByUsedInFinancingActivities
A76: Effect of exchange rates on cash | B76: 63 | C76: EffectOfExchangeRateOnCashCashEquivalentsRestrictedCashAndRestrictedCashEquivalentsIncludingDisposalGroupAndDiscontinuedOperations
A77: Net change in cash | B77: =B68+B71+B75+B76 -> 11927 | C77: Calculated
A78: Memo
A79: Free cash flow (operating cash flow - capex) | B79: =B68+B69 -> 71611 | C79: Calculated

Sheet NVDA
A1: Nvidia (NVDA)
A2: Form 10-K, accession 0001045810-26-000021. USD millions, except per-share data; shares in millions.
A4: Fiscal year ended | B4: 2026-01-25 | C4: Source (us-gaap XBRL tag)
A5: INCOME STATEMENT
A6: Revenue | B6: 215938 | C6: Revenues
A7: Cost of revenue | B7: 62475 | C7: CostOfRevenue
A8: Gross profit | B8: 153463 | C8: GrossProfit
A9: Research and development | B9: 18497 | C9: ResearchAndDevelopmentExpense
A10: Selling, general and administrative | B10: 4579 | C10: SellingGeneralAndAdministrativeExpense
A11: of which: sales and marketing | C11: Not reported under a standard tag
A12: of which: general and administrative | C12: Not reported under a standard tag
A13: Other operating expenses, net (residual) | B13: =B6-B7-B9-B10-B15 -> 0 | C13: Calculated
A14: Total costs and expenses | B14: =B6-B15 -> 85551 | C14: Calculated
A15: Operating income | B15: 130387 | C15: OperatingIncomeLoss
A16: Non-operating income (expense), net | B16: =B19-B15 -> 11063 | C16: Calculated
A17: of which: interest and investment income | B17: 2300 | C17: InvestmentIncomeInterest
A18: of which: interest expense | B18: 259 | C18: InterestExpenseNonoperating
A19: Income before income taxes | B19: 141450 | C19: IncomeLossFromContinuingOperationsBeforeIncomeTaxesExtraordinaryItemsNoncontrollingInterest
A20: Provision for income taxes | B20: 21383 | C20: IncomeTaxExpenseBenefit
A21: Equity-method, discontinued operations and other, net | B21: =B22-B19+B20 -> 0 | C21: Calculated
A22: Net income | B22: 120067 | C22: NetIncomeLoss
A23: EPS, basic (USD) | B23: 4.93 | C23: EarningsPerShareBasic
A24: EPS, diluted (USD) | B24: 4.9 | C24: EarningsPerShareDiluted
A25: Weighted average shares, basic | B25: 24359 | C25: WeightedAverageNumberOfSharesOutstandingBasic
A26: Weighted average shares, diluted | B26: 24514 | C26: WeightedAverageNumberOfDilutedSharesOutstanding
A27: Memo
A28: Depreciation and amortization | B28: 2843 | C28: DepreciationDepletionAndAmortization
A29: Amortization of intangible assets | B29: 488 | C29: AmortizationOfIntangibleAssets
A30: Stock-based compensation | B30: 6386 | C30: ShareBasedCompensation
A31: EBITDA (operating income + D&A) | B31: =B15+B28 -> 133230 | C31: Calculated
A33: BALANCE SHEET
A34: Cash and cash equivalents | B34: 10605 | C34: CashAndCashEquivalentsAtCarryingValue
A35: Short-term investments / marketable securities | C35: Not reported under a standard tag
A36: Accounts receivable, net | B36: 38466 | C36: AccountsReceivableNetCurrent
A37: Inventories | B37: 21403 | C37: InventoryNet
A38: Other current assets (residual) | B38: =B39-B34-B35-B36-B37 -> 55131 | C38: Calculated
A39: Total current assets | B39: 125605 | C39: AssetsCurrent
A40: Property and equipment, net | B40: 10383 | C40: PropertyPlantAndEquipmentNet
A41: Operating lease right-of-use assets | B41: 2867 | C41: OperatingLeaseRightOfUseAsset
A42: Goodwill | B42: 20832 | C42: Goodwill
A43: Intangible assets, net | B43: 3306 | C43: IntangibleAssetsNetExcludingGoodwill
A44: Other non-current assets (residual) | B44: =B45-B39-B40-B41-B42-B43 -> 43810 | C44: Calculated
A45: Total assets | B45: 206803 | C45: Assets
A46: Accounts payable | B46: 9812 | C46: AccountsPayableCurrent
A47: Deferred / unearned revenue, current | B47: 1379 | C47: ContractWithCustomerLiabilityCurrent
A48: Short-term debt and current portion of long-term debt | B48: 999 | C48: DebtCurrent
A49: Other current liabilities (residual) | B49: =B50-B46-B47-B48 -> 19973 | C49: Calculated
A50: Total current liabilities | B50: 32163 | C50: LiabilitiesCurrent
A51: Long-term debt | B51: 7469 | C51: LongTermDebtNoncurrent
A52: Other non-current liabilities (residual) | B52: =B53-B50-B51 -> 9878 | C52: Calculated
A53: Total liabilities | B53: 49510 | C53: Liabilities
A54: Total stockholders' equity | B54: 157293 | C54: StockholdersEquity
A55: Total liabilities and equity | B55: 206803 | C55: LiabilitiesAndStockholdersEquity
A56: Check: assets - liabilities and equity | B56: =B45-B55 -> 0 | C56: Calculated
A57: Memo
A58: Total debt (excl. leases) | B58: =B48+B51 -> 8468 | C58: Calculated
A59: Cash and short-term investments | B59: =B34+B35 -> 10605 | C59: Calculated
A60: Net debt | B60: =B58-B59 -> -2137 | C60: Calculated
A61: Common shares outstanding | B61: 24304 | C61: CommonStockSharesOutstanding
A63: CASH FLOW STATEMENT
A64: Net income | B64: =B22 -> 120067 | C64: Calculated
A65: Depreciation and amortization | B65: =B28 -> 2843 | C65: Calculated
A66: Stock-based compensation | B66: =B30 -> 6386 | C66: Calculated
A67: Other adjustments and working capital (residual) | B67: =B68-B64-B65-B66 -> -26578 | C67: Calculated
A68: Net cash from operating activities | B68: 102718 | C68: NetCashProvidedByUsedInOperatingActivities
A69: Capital expenditures | B69: -6042 | C69: PaymentsToAcquireProductiveAssets
A70: Other investing activities (residual) | B70: =B71-B69 -> -46186 | C70: Calculated
A71: Net cash from investing activities | B71: -52228 | C71: NetCashProvidedByUsedInInvestingActivities
A72: Repurchases of common stock | B72: -40086 | C72: PaymentsForRepurchaseOfCommonStock
A73: Dividends paid | B73: -974 | C73: PaymentsOfDividends
A74: Other financing activities (residual) | B74: =B75-B72-B73 -> -7414 | C74: Calculated
A75: Net cash from financing activities | B75: -48474 | C75: NetCashProvidedByUsedInFinancingActivities
A76: Effect of exchange rates on cash | C76: Not reported under a standard tag
A77: Net change in cash | B77: =B68+B71+B75+B76 -> 2016 | C77: Calculated
A78: Memo
A79: Free cash flow (operating cash flow - capex) | B79: =B68+B69 -> 96676 | C79: Calculated

Sheet GOOGL
A1: Alphabet (GOOGL)
A2: Form 10-K, accession 0001652044-26-000018. USD millions, except per-share data; shares in millions.
A4: Fiscal year ended | B4: 2025-12-31 | C4: Source (us-gaap XBRL tag)
A5: INCOME STATEMENT
A6: Revenue | B6: 402836 | C6: Revenues
A7: Cost of revenue | B7: 162535 | C7: CostOfRevenue
A8: Gross profit | B8: =B6-B7 -> 240301 | C8: Calculated
A9: Research and development | B9: 61087 | C9: ResearchAndDevelopmentExpense
A10: Selling, general and administrative | B10: =B11+B12 -> 50175 | C10: Calculated
A11: of which: sales and marketing | B11: 28693 | C11: SellingAndMarketingExpense
A12: of which: general and administrative | B12: 21482 | C12: GeneralAndAdministrativeExpense
A13: Other operating expenses, net (residual) | B13: =B6-B7-B9-B10-B15 -> 0 | C13: Calculated
A14: Total costs and expenses | B14: =B6-B15 -> 273797 | C14: Calculated
A15: Operating income | B15: 129039 | C15: OperatingIncomeLoss
A16: Non-operating income (expense), net | B16: =B19-B15 -> 29787 | C16: Calculated
A17: of which: interest and investment income | B17: 4337 | C17: InterestIncomeOther
A18: of which: interest expense | B18: 736 | C18: InterestExpenseNonoperating
A19: Income before income taxes | B19: 158826 | C19: IncomeLossFromContinuingOperationsBeforeIncomeTaxesExtraordinaryItemsNoncontrollingInterest
A20: Provision for income taxes | B20: 26656 | C20: IncomeTaxExpenseBenefit
A21: Equity-method, discontinued operations and other, net | B21: =B22-B19+B20 -> 0 | C21: Calculated
A22: Net income | B22: 132170 | C22: NetIncomeLoss
A23: EPS, basic (USD) | B23: 10.91 | C23: EarningsPerShareBasic
A24: EPS, diluted (USD) | B24: 10.81 | C24: EarningsPerShareDiluted
A25: Weighted average shares, basic | B25: 12116 | C25: WeightedAverageNumberOfSharesOutstandingBasic
A26: Weighted average shares, diluted | B26: 12230 | C26: WeightedAverageNumberOfDilutedSharesOutstanding
A27: Memo
A28: Depreciation and amortization | B28: 21136 | C28: Depreciation
A29: Amortization of intangible assets | C29: Not reported under a standard tag
A30: Stock-based compensation | B30: 24953 | C30: ShareBasedCompensation
A31: EBITDA (operating income + D&A) | B31: =B15+B28 -> 150175 | C31: Calculated
A33: BALANCE SHEET
A34: Cash and cash equivalents | B34: 30708 | C34: CashAndCashEquivalentsAtCarryingValue
A35: Short-term investments / marketable securities | B35: 96135 | C35: MarketableSecuritiesCurrent
A36: Accounts receivable, net | B36: 62886 | C36: AccountsReceivableNetCurrent
A37: Inventories | C37: Not reported under a standard tag
A38: Other current assets (residual) | B38: =B39-B34-B35-B36-B37 -> 16309 | C38: Calculated
A39: Total current assets | B39: 206038 | C39: AssetsCurrent
A40: Property and equipment, net | B40: 246597 | C40: PropertyPlantAndEquipmentAndFinanceLeaseRightOfUseAssetAfterAccumulatedDepreciationAndAmortization
A41: Operating lease right-of-use assets | B41: 15221 | C41: OperatingLeaseRightOfUseAsset
A42: Goodwill | B42: 33380 | C42: Goodwill
A43: Intangible assets, net | C43: Not reported under a standard tag
A44: Other non-current assets (residual) | B44: =B45-B39-B40-B41-B42-B43 -> 94045 | C44: Calculated
A45: Total assets | B45: 595281 | C45: Assets
A46: Accounts payable | B46: 12200 | C46: AccountsPayableCurrent
A47: Deferred / unearned revenue, current | B47: 6578 | C47: ContractWithCustomerLiabilityCurrent
A48: Short-term debt and current portion of long-term debt | B48: 1996 | C48: LongTermDebtCurrent + CommercialPaper
A49: Other current liabilities (residual) | B49: =B50-B46-B47-B48 -> 81971 | C49: Calculated
A50: Total current liabilities | B50: 102745 | C50: LiabilitiesCurrent
A51: Long-term debt | B51: 46547 | C51: LongTermDebtNoncurrent
A52: Other non-current liabilities (residual) | B52: =B53-B50-B51 -> 30724 | C52: Calculated
A53: Total liabilities | B53: 180016 | C53: Liabilities
A54: Total stockholders' equity | B54: 415265 | C54: StockholdersEquity
A55: Total liabilities and equity | B55: 595281 | C55: LiabilitiesAndStockholdersEquity
A56: Check: assets - liabilities and equity | B56: =B45-B55 -> 0 | C56: Calculated
A57: Memo
A58: Total debt (excl. leases) | B58: =B48+B51 -> 48543 | C58: Calculated
A59: Cash and short-term investments | B59: =B34+B35 -> 126843 | C59: Calculated
A60: Net debt | B60: =B58-B59 -> -78300 | C60: Calculated
A61: Common shares outstanding | B61: 12088 | C61: CommonStockSharesOutstanding
A63: CASH FLOW STATEMENT
A64: Net income | B64: =B22 -> 132170 | C64: Calculated
A65: Depreciation and amortization | B65: =B28 -> 21136 | C65: Calculated
A66: Stock-based compensation | B66: =B30 -> 24953 | C66: Calculated
A67: Other adjustments and working capital (residual) | B67: =B68-B64-B65-B66 -> -13546 | C67: Calculated
A68: Net cash from operating activities | B68: 164713 | C68: NetCashProvidedByUsedInOperatingActivities
A69: Capital expenditures | B69: -91447 | C69: PaymentsToAcquirePropertyPlantAndEquipment
A70: Other investing activities (residual) | B70: =B71-B69 -> -28844 | C70: Calculated
A71: Net cash from investing activities | B71: -120291 | C71: NetCashProvidedByUsedInInvestingActivities
A72: Repurchases of common stock | B72: -45709 | C72: PaymentsForRepurchaseOfCommonStock
A73: Dividends paid | B73: -10049 | C73: PaymentsOfDividends
A74: Other financing activities (residual) | B74: =B75-B72-B73 -> 18370 | C74: Calculated
A75: Net cash from financing activities | B75: -37388 | C75: NetCashProvidedByUsedInFinancingActivities
A76: Effect of exchange rates on cash | B76: 208 | C76: EffectOfExchangeRateOnCashCashEquivalentsRestrictedCashAndRestrictedCashEquivalents
A77: Net change in cash | B77: =B68+B71+B75+B76 -> 7242 | C77: Calculated
A78: Memo
A79: Free cash flow (operating cash flow - capex) | B79: =B68+B69 -> 73266 | C79: Calculated

Sheet META
A1: Meta Platforms (META)
A2: Form 10-K, accession 0001628280-26-003942. USD millions, except per-share data; shares in millions.
A4: Fiscal year ended | B4: 2025-12-31 | C4: Source (us-gaap XBRL tag)
A5: INCOME STATEMENT
A6: Revenue | B6: 200966 | C6: RevenueFromContractWithCustomerExcludingAssessedTax
A7: Cost of revenue | B7: 36175 | C7: CostOfRevenue
A8: Gross profit | B8: =B6-B7 -> 164791 | C8: Calculated
A9: Research and development | B9: 57372 | C9: ResearchAndDevelopmentExpense
A10: Selling, general and administrative | B10: =B11+B12 -> 24143 | C10: Calculated
A11: of which: sales and marketing | B11: 11991 | C11: SellingAndMarketingExpense
A12: of which: general and administrative | B12: 12152 | C12: GeneralAndAdministrativeExpense
A13: Other operating expenses, net (residual) | B13: =B6-B7-B9-B10-B15 -> 0 | C13: Calculated
A14: Total costs and expenses | B14: =B6-B15 -> 117690 | C14: Calculated
A15: Operating income | B15: 83276 | C15: OperatingIncomeLoss
A16: Non-operating income (expense), net | B16: =B19-B15 -> 2656 | C16: Calculated
A17: of which: interest and investment income | B17: 2123 | C17: InvestmentIncomeInterest
A18: of which: interest expense | B18: 1165 | C18: InterestExpenseNonoperating
A19: Income before income taxes | B19: 85932 | C19: IncomeLossFromContinuingOperationsBeforeIncomeTaxesExtraordinaryItemsNoncontrollingInterest
A20: Provision for income taxes | B20: 25474 | C20: IncomeTaxExpenseBenefit
A21: Equity-method, discontinued operations and other, net | B21: =B22-B19+B20 -> 0 | C21: Calculated
A22: Net income | B22: 60458 | C22: NetIncomeLoss
A23: EPS, basic (USD) | B23: 23.98 | C23: EarningsPerShareBasic
A24: EPS, diluted (USD) | B24: 23.49 | C24: EarningsPerShareDiluted
A25: Weighted average shares, basic | B25: 2521 | C25: WeightedAverageNumberOfSharesOutstandingBasic
A26: Weighted average shares, diluted | B26: 2574 | C26: WeightedAverageNumberOfDilutedSharesOutstanding
A27: Memo
A28: Depreciation and amortization | B28: 18616 | C28: DepreciationDepletionAndAmortization
A29: Amortization of intangible assets | B29: 615 | C29: AmortizationOfIntangibleAssets
A30: Stock-based compensation | B30: 20427 | C30: ShareBasedCompensation
A31: EBITDA (operating income + D&A) | B31: =B15+B28 -> 101892 | C31: Calculated
A33: BALANCE SHEET
A34: Cash and cash equivalents | B34: 35873 | C34: CashAndCashEquivalentsAtCarryingValue
A35: Short-term investments / marketable securities | B35: 45719 | C35: MarketableSecuritiesCurrent
A36: Accounts receivable, net | B36: 19769 | C36: AccountsReceivableNetCurrent
A37: Inventories | C37: Not reported under a standard tag
A38: Other current assets (residual) | B38: =B39-B34-B35-B36-B37 -> 7361 | C38: Calculated
A39: Total current assets | B39: 108722 | C39: AssetsCurrent
A40: Property and equipment, net | B40: 176400 | C40: PropertyPlantAndEquipmentAndFinanceLeaseRightOfUseAssetAfterAccumulatedDepreciationAndAmortization
A41: Operating lease right-of-use assets | B41: 20404 | C41: OperatingLeaseRightOfUseAsset
A42: Goodwill | B42: 24534 | C42: Goodwill
A43: Intangible assets, net | B43: 3692 | C43: IntangibleAssetsNetExcludingGoodwill
A44: Other non-current assets (residual) | B44: =B45-B39-B40-B41-B42-B43 -> 32269 | C44: Calculated
A45: Total assets | B45: 366021 | C45: Assets
A46: Accounts payable | B46: 8894 | C46: AccountsPayableTradeCurrent
A47: Deferred / unearned revenue, current | C47: Not reported under a standard tag
A48: Short-term debt and current portion of long-term debt | C48: Not reported under a standard tag
A49: Other current liabilities (residual) | B49: =B50-B46-B47-B48 -> 32942 | C49: Calculated
A50: Total current liabilities | B50: 41836 | C50: LiabilitiesCurrent
A51: Long-term debt | B51: 58744 | C51: LongTermDebtNoncurrent
A52: Other non-current liabilities (residual) | B52: =B53-B50-B51 -> 48198 | C52: Calculated
A53: Total liabilities | B53: 148778 | C53: Liabilities
A54: Total stockholders' equity | B54: 217243 | C54: StockholdersEquity
A55: Total liabilities and equity | B55: 366021 | C55: LiabilitiesAndStockholdersEquity
A56: Check: assets - liabilities and equity | B56: =B45-B55 -> 0 | C56: Calculated
A57: Memo
A58: Total debt (excl. leases) | B58: =B48+B51 -> 58744 | C58: Calculated
A59: Cash and short-term investments | B59: =B34+B35 -> 81592 | C59: Calculated
A60: Net debt | B60: =B58-B59 -> -22848 | C60: Calculated
A61: Common shares outstanding | C61: Not reported under a standard tag
A63: CASH FLOW STATEMENT
A64: Net income | B64: =B22 -> 60458 | C64: Calculated
A65: Depreciation and amortization | B65: =B28 -> 18616 | C65: Calculated
A66: Stock-based compensation | B66: =B30 -> 20427 | C66: Calculated
A67: Other adjustments and working capital (residual) | B67: =B68-B64-B65-B66 -> 16299 | C67: Calculated
A68: Net cash from operating activities | B68: 115800 | C68: NetCashProvidedByUsedInOperatingActivities
A69: Capital expenditures | B69: -69691 | C69: PaymentsToAcquirePropertyPlantAndEquipment
A70: Other investing activities (residual) | B70: =B71-B69 -> -32312 | C70: Calculated
A71: Net cash from investing activities | B71: -102003 | C71: NetCashProvidedByUsedInInvestingActivities
A72: Repurchases of common stock | B72: -26248 | C72: PaymentsForRepurchaseOfCommonStock
A73: Dividends paid | B73: -5324 | C73: PaymentsOfDividends
A74: Other financing activities (residual) | B74: =B75-B72-B73 -> 11202 | C74: Calculated
A75: Net cash from financing activities | B75: -20370 | C75: NetCashProvidedByUsedInFinancingActivities
A76: Effect of exchange rates on cash | B76: 235 | C76: EffectOfExchangeRateOnCashCashEquivalentsRestrictedCashAndRestrictedCashEquivalents
A77: Net change in cash | B77: =B68+B71+B75+B76 -> -6338 | C77: Calculated
A78: Memo
A79: Free cash flow (operating cash flow - capex) | B79: =B68+B69 -> 46109 | C79: Calculated

Sheet AAPL
A1: Apple (AAPL)
A2: Form 10-K, accession 0000320193-25-000079. USD millions, except per-share data; shares in millions.
A4: Fiscal year ended | B4: 2025-09-27 | C4: Source (us-gaap XBRL tag)
A5: INCOME STATEMENT
A6: Revenue | B6: 416161 | C6: RevenueFromContractWithCustomerExcludingAssessedTax
A7: Cost of revenue | B7: 220960 | C7: CostOfGoodsAndServicesSold
A8: Gross profit | B8: 195201 | C8: GrossProfit
A9: Research and development | B9: 34550 | C9: ResearchAndDevelopmentExpense
A10: Selling, general and administrative | B10: 27601 | C10: SellingGeneralAndAdministrativeExpense
A11: of which: sales and marketing | B11: 19524 | C11: SellingAndMarketingExpense
A12: of which: general and administrative | B12: 8077 | C12: GeneralAndAdministrativeExpense
A13: Other operating expenses, net (residual) | B13: =B6-B7-B9-B10-B15 -> 0 | C13: Calculated
A14: Total costs and expenses | B14: =B6-B15 -> 283111 | C14: Calculated
A15: Operating income | B15: 133050 | C15: OperatingIncomeLoss
A16: Non-operating income (expense), net | B16: =B19-B15 -> -321 | C16: Calculated
A17: of which: interest and investment income | C17: Not reported under a standard tag
A18: of which: interest expense | C18: Not reported under a standard tag
A19: Income before income taxes | B19: 132729 | C19: IncomeLossFromContinuingOperationsBeforeIncomeTaxesExtraordinaryItemsNoncontrollingInterest
A20: Provision for income taxes | B20: 20719 | C20: IncomeTaxExpenseBenefit
A21: Equity-method, discontinued operations and other, net | B21: =B22-B19+B20 -> 0 | C21: Calculated
A22: Net income | B22: 112010 | C22: NetIncomeLoss
A23: EPS, basic (USD) | B23: 7.49 | C23: EarningsPerShareBasic
A24: EPS, diluted (USD) | B24: 7.46 | C24: EarningsPerShareDiluted
A25: Weighted average shares, basic | B25: 14948.5 | C25: WeightedAverageNumberOfSharesOutstandingBasic
A26: Weighted average shares, diluted | B26: 15004.697 | C26: WeightedAverageNumberOfDilutedSharesOutstanding
A27: Memo
A28: Depreciation and amortization | B28: 11698 | C28: DepreciationDepletionAndAmortization
A29: Amortization of intangible assets | C29: Not reported under a standard tag
A30: Stock-based compensation | B30: 12863 | C30: ShareBasedCompensation
A31: EBITDA (operating income + D&A) | B31: =B15+B28 -> 144748 | C31: Calculated
A33: BALANCE SHEET
A34: Cash and cash equivalents | B34: 35934 | C34: CashAndCashEquivalentsAtCarryingValue
A35: Short-term investments / marketable securities | B35: 18763 | C35: MarketableSecuritiesCurrent
A36: Accounts receivable, net | B36: 39777 | C36: AccountsReceivableNetCurrent
A37: Inventories | B37: 5718 | C37: InventoryNet
A38: Other current assets (residual) | B38: =B39-B34-B35-B36-B37 -> 47765 | C38: Calculated
A39: Total current assets | B39: 147957 | C39: AssetsCurrent
A40: Property and equipment, net | B40: 49834 | C40: PropertyPlantAndEquipmentNet
A41: Operating lease right-of-use assets | B41: 11205 | C41: OperatingLeaseRightOfUseAsset
A42: Goodwill | C42: Not reported under a standard tag
A43: Intangible assets, net | C43: Not reported under a standard tag
A44: Other non-current assets (residual) | B44: =B45-B39-B40-B41-B42-B43 -> 150245 | C44: Calculated
A45: Total assets | B45: 359241 | C45: Assets
A46: Accounts payable | B46: 69860 | C46: AccountsPayableCurrent
A47: Deferred / unearned revenue, current | B47: 9055 | C47: ContractWithCustomerLiabilityCurrent
A48: Short-term debt and current portion of long-term debt | B48: 20329 | C48: LongTermDebtCurrent + CommercialPaper
A49: Other current liabilities (residual) | B49: =B50-B46-B47-B48 -> 66387 | C49: Calculated
A50: Total current liabilities | B50: 165631 | C50: LiabilitiesCurrent
A51: Long-term debt | B51: 78328 | C51: LongTermDebtNoncurrent
A52: Other non-current liabilities (residual) | B52: =B53-B50-B51 -> 41549 | C52: Calculated
A53: Total liabilities | B53: 285508 | C53: Liabilities
A54: Total stockholders' equity | B54: 73733 | C54: StockholdersEquity
A55: Total liabilities and equity | B55: 359241 | C55: LiabilitiesAndStockholdersEquity
A56: Check: assets - liabilities and equity | B56: =B45-B55 -> 0 | C56: Calculated
A57: Memo
A58: Total debt (excl. leases) | B58: =B48+B51 -> 98657 | C58: Calculated
A59: Cash and short-term investments | B59: =B34+B35 -> 54697 | C59: Calculated
A60: Net debt | B60: =B58-B59 -> 43960 | C60: Calculated
A61: Common shares outstanding | B61: 14773.26 | C61: CommonStockSharesOutstanding
A63: CASH FLOW STATEMENT
A64: Net income | B64: =B22 -> 112010 | C64: Calculated
A65: Depreciation and amortization | B65: =B28 -> 11698 | C65: Calculated
A66: Stock-based compensation | B66: =B30 -> 12863 | C66: Calculated
A67: Other adjustments and working capital (residual) | B67: =B68-B64-B65-B66 -> -25089 | C67: Calculated
A68: Net cash from operating activities | B68: 111482 | C68: NetCashProvidedByUsedInOperatingActivities
A69: Capital expenditures | B69: -12715 | C69: PaymentsToAcquirePropertyPlantAndEquipment
A70: Other investing activities (residual) | B70: =B71-B69 -> 27910 | C70: Calculated
A71: Net cash from investing activities | B71: 15195 | C71: NetCashProvidedByUsedInInvestingActivities
A72: Repurchases of common stock | B72: -90711 | C72: PaymentsForRepurchaseOfCommonStock
A73: Dividends paid | B73: -15421 | C73: PaymentsOfDividends
A74: Other financing activities (residual) | B74: =B75-B72-B73 -> -14554 | C74: Calculated
A75: Net cash from financing activities | B75: -120686 | C75: NetCashProvidedByUsedInFinancingActivities
A76: Effect of exchange rates on cash | C76: Not reported under a standard tag
A77: Net change in cash | B77: =B68+B71+B75+B76 -> 5991 | C77: Calculated
A78: Memo
A79: Free cash flow (operating cash flow - capex) | B79: =B68+B69 -> 98767 | C79: Calculated

Sheet AVGO
A1: Broadcom (AVGO)
A2: Form 10-K, accession 0001730168-25-000121. USD millions, except per-share data; shares in millions.
A4: Fiscal year ended | B4: 2025-11-02 | C4: Source (us-gaap XBRL tag)
A5: INCOME STATEMENT
A6: Revenue | B6: 63887 | C6: RevenueFromContractWithCustomerExcludingAssessedTax
A7: Cost of revenue | B7: 20593 | C7: CostOfRevenue
A8: Gross profit | B8: 43294 | C8: GrossProfit
A9: Research and development | B9: 10977 | C9: ResearchAndDevelopmentExpense
A10: Selling, general and administrative | B10: 4211 | C10: SellingGeneralAndAdministrativeExpense
A11: of which: sales and marketing | C11: Not reported under a standard tag
A12: of which: general and administrative | C12: Not reported under a standard tag
A13: Other operating expenses, net (residual) | B13: =B6-B7-B9-B10-B15 -> 2622 | C13: Calculated
A14: Total costs and expenses | B14: =B6-B15 -> 38403 | C14: Calculated
A15: Operating income | B15: 25484 | C15: OperatingIncomeLoss
A16: Non-operating income (expense), net | B16: =B19-B15 -> -2755 | C16: Calculated
A17: of which: interest and investment income | B17: 347 | C17: InterestIncomeOther
A18: of which: interest expense | B18: 3210 | C18: InterestExpenseNonoperating
A19: Income before income taxes | B19: 22729 | C19: IncomeLossFromContinuingOperationsBeforeIncomeTaxesExtraordinaryItemsNoncontrollingInterest
A20: Provision for income taxes | B20: -397 | C20: IncomeTaxExpenseBenefit
A21: Equity-method, discontinued operations and other, net | B21: =B22-B19+B20 -> 0 | C21: Calculated
A22: Net income | B22: 23126 | C22: ProfitLoss
A23: EPS, basic (USD) | B23: 4.91 | C23: EarningsPerShareBasic
A24: EPS, diluted (USD) | B24: 4.77 | C24: EarningsPerShareDiluted
A25: Weighted average shares, basic | B25: 4712 | C25: WeightedAverageNumberOfSharesOutstandingBasic
A26: Weighted average shares, diluted | B26: 4853 | C26: WeightedAverageNumberOfDilutedSharesOutstanding
A27: Memo
A28: Depreciation and amortization | B28: 8636 | C28: Depreciation + AmortizationOfIntangibleAssets
A29: Amortization of intangible assets | B29: 8062 | C29: AmortizationOfIntangibleAssets
A30: Stock-based compensation | B30: 7568 | C30: ShareBasedCompensation
A31: EBITDA (operating income + D&A) | B31: =B15+B28 -> 34120 | C31: Calculated
A33: BALANCE SHEET
A34: Cash and cash equivalents | B34: 16178 | C34: CashAndCashEquivalentsAtCarryingValue
A35: Short-term investments / marketable securities | C35: Not reported under a standard tag
A36: Accounts receivable, net | B36: 7145 | C36: AccountsReceivableNetCurrent
A37: Inventories | B37: 2270 | C37: InventoryNet
A38: Other current assets (residual) | B38: =B39-B34-B35-B36-B37 -> 5980 | C38: Calculated
A39: Total current assets | B39: 31573 | C39: AssetsCurrent
A40: Property and equipment, net | B40: 2530 | C40: PropertyPlantAndEquipmentNet
A41: Operating lease right-of-use assets | B41: 1318 | C41: OperatingLeaseRightOfUseAsset
A42: Goodwill | B42: 97801 | C42: Goodwill
A43: Intangible assets, net | B43: 32273 | C43: IntangibleAssetsNetExcludingGoodwill
A44: Other non-current assets (residual) | B44: =B45-B39-B40-B41-B42-B43 -> 5597 | C44: Calculated
A45: Total assets | B45: 171092 | C45: Assets
A46: Accounts payable | B46: 1560 | C46: AccountsPayableCurrent
A47: Deferred / unearned revenue, current | B47: 9469 | C47: ContractWithCustomerLiabilityCurrent
A48: Short-term debt and current portion of long-term debt | B48: 3152 | C48: LongTermDebtCurrent
A49: Other current liabilities (residual) | B49: =B50-B46-B47-B48 -> 4333 | C49: Calculated
A50: Total current liabilities | B50: 18514 | C50: LiabilitiesCurrent
A51: Long-term debt | B51: 61984 | C51: LongTermDebtAndCapitalLeaseObligations
A52: Other non-current liabilities (residual) | B52: =B53-B50-B51 -> 9302 | C52: Calculated
A53: Total liabilities | B53: 89800 | C53: Liabilities
A54: Total stockholders' equity | B54: 81292 | C54: StockholdersEquityIncludingPortionAttributableToNoncontrollingInterest
A55: Total liabilities and equity | B55: 171092 | C55: LiabilitiesAndStockholdersEquity
A56: Check: assets - liabilities and equity | B56: =B45-B55 -> 0 | C56: Calculated
A57: Memo
A58: Total debt (excl. leases) | B58: =B48+B51 -> 65136 | C58: Calculated
A59: Cash and short-term investments | B59: =B34+B35 -> 16178 | C59: Calculated
A60: Net debt | B60: =B58-B59 -> 48958 | C60: Calculated
A61: Common shares outstanding | B61: 4741 | C61: CommonStockSharesOutstanding
A63: CASH FLOW STATEMENT
A64: Net income | B64: =B22 -> 23126 | C64: Calculated
A65: Depreciation and amortization | B65: =B28 -> 8636 | C65: Calculated
A66: Stock-based compensation | B66: =B30 -> 7568 | C66: Calculated
A67: Other adjustments and working capital (residual) | B67: =B68-B64-B65-B66 -> -11793 | C67: Calculated
A68: Net cash from operating activities | B68: 27537 | C68: NetCashProvidedByUsedInOperatingActivities
A69: Capital expenditures | B69: -623 | C69: PaymentsToAcquirePropertyPlantAndEquipment
A70: Other investing activities (residual) | B70: =B71-B69 -> 43 | C70: Calculated
A71: Net cash from investing activities | B71: -580 | C71: NetCashProvidedByUsedInInvestingActivities
A72: Repurchases of common stock | B72: -2450 | C72: PaymentsForRepurchaseOfCommonStock
A73: Dividends paid | B73: -11142 | C73: PaymentsOfDividends
A74: Other financing activities (residual) | B74: =B75-B72-B73 -> -6535 | C74: Calculated
A75: Net cash from financing activities | B75: -20127 | C75: NetCashProvidedByUsedInFinancingActivities
A76: Effect of exchange rates on cash | C76: Not reported under a standard tag
A77: Net change in cash | B77: =B68+B71+B75+B76 -> 6830 | C77: Calculated
A78: Memo
A79: Free cash flow (operating cash flow - capex) | B79: =B68+B69 -> 26914 | C79: Calculated

Sheet NOW
A1: ServiceNow (NOW)
A2: Form 10-K, accession 0001373715-26-000007. USD millions, except per-share data; shares in millions.
A4: Fiscal year ended | B4: 2025-12-31 | C4: Source (us-gaap XBRL tag)
A5: INCOME STATEMENT
A6: Revenue | B6: 13278 | C6: RevenueFromContractWithCustomerExcludingAssessedTax
A7: Cost of revenue | B7: 2983 | C7: CostOfRevenue
A8: Gross profit | B8: 10295 | C8: GrossProfit
A9: Research and development | B9: 2960 | C9: ResearchAndDevelopmentExpense
A10: Selling, general and administrative | B10: =B11+B12 -> 5511 | C10: Calculated
A11: of which: sales and marketing | B11: 4388 | C11: SellingAndMarketingExpense
A12: of which: general and administrative | B12: 1123 | C12: GeneralAndAdministrativeExpense
A13: Other operating expenses, net (residual) | B13: =B6-B7-B9-B10-B15 -> 0 | C13: Calculated
A14: Total costs and expenses | B14: =B6-B15 -> 11454 | C14: Calculated
A15: Operating income | B15: 1824 | C15: OperatingIncomeLoss
A16: Non-operating income (expense), net | B16: =B19-B15 -> 437 | C16: Calculated
A17: of which: interest and investment income | C17: Not reported under a standard tag
A18: of which: interest expense | C18: Not reported under a standard tag
A19: Income before income taxes | B19: 2261 | C19: IncomeLossFromContinuingOperationsBeforeIncomeTaxesExtraordinaryItemsNoncontrollingInterest
A20: Provision for income taxes | B20: 513 | C20: IncomeTaxExpenseBenefit
A21: Equity-method, discontinued operations and other, net | B21: =B22-B19+B20 -> 0 | C21: Calculated
A22: Net income | B22: 1748 | C22: NetIncomeLoss
A23: EPS, basic (USD) | B23: 1.69 | C23: EarningsPerShareBasic
A24: EPS, diluted (USD) | B24: 1.67 | C24: EarningsPerShareDiluted
A25: Weighted average shares, basic | B25: 1036.74 | C25: WeightedAverageNumberOfSharesOutstandingBasic
A26: Weighted average shares, diluted | B26: 1046.691 | C26: WeightedAverageNumberOfDilutedSharesOutstanding
A27: Memo
A28: Depreciation and amortization | B28: 738 | C28: DepreciationDepletionAndAmortization
A29: Amortization of intangible assets | B29: 120 | C29: AmortizationOfIntangibleAssets
A30: Stock-based compensation | B30: 1955 | C30: ShareBasedCompensation
A31: EBITDA (operating income + D&A) | B31: =B15+B28 -> 2562 | C31: Calculated
A33: BALANCE SHEET
A34: Cash and cash equivalents | B34: 3726 | C34: CashAndCashEquivalentsAtCarryingValue
A35: Short-term investments / marketable securities | B35: 2558 | C35: AvailableForSaleSecuritiesDebtSecuritiesCurrent
A36: Accounts receivable, net | B36: 2627 | C36: AccountsReceivableNetCurrent
A37: Inventories | C37: Not reported under a standard tag
A38: Other current assets (residual) | B38: =B39-B34-B35-B36-B37 -> 1560 | C38: Calculated
A39: Total current assets | B39: 10471 | C39: AssetsCurrent
A40: Property and equipment, net | B40: 2289 | C40: PropertyPlantAndEquipmentNet
A41: Operating lease right-of-use assets | B41: 806 | C41: OperatingLeaseRightOfUseAsset
A42: Goodwill | B42: 3578 | C42: Goodwill
A43: Intangible assets, net | B43: 1121 | C43: IntangibleAssetsNetExcludingGoodwill
A44: Other non-current assets (residual) | B44: =B45-B39-B40-B41-B42-B43 -> 7773 | C44: Calculated
A45: Total assets | B45: 26038 | C45: Assets
A46: Accounts payable | B46: 204 | C46: AccountsPayableCurrent
A47: Deferred / unearned revenue, current | B47: 8314 | C47: ContractWithCustomerLiabilityCurrent
A48: Short-term debt and current portion of long-term debt | C48: Not reported under a standard tag
A49: Other current liabilities (residual) | B49: =B50-B46-B47-B48 -> 1925 | C49: Calculated
A50: Total current liabilities | B50: 10443 | C50: LiabilitiesCurrent
A51: Long-term debt | B51: 1491 | C51: ConvertibleLongTermNotesPayable
A52: Other non-current liabilities (residual) | B52: =B53-B50-B51 -> 1140 | C52: Calculated
A53: Total liabilities | B53: 13074 | C53: Liabilities
A54: Total stockholders' equity | B54: 12964 | C54: StockholdersEquity
A55: Total liabilities and equity | B55: 26038 | C55: LiabilitiesAndStockholdersEquity
A56: Check: assets - liabilities and equity | B56: =B45-B55 -> 0 | C56: Calculated
A57: Memo
A58: Total debt (excl. leases) | B58: =B48+B51 -> 1491 | C58: Calculated
A59: Cash and short-term investments | B59: =B34+B35 -> 6284 | C59: Calculated
A60: Net debt | B60: =B58-B59 -> -4793 | C60: Calculated
A61: Common shares outstanding | B61: 1047.278 | C61: CommonStockSharesOutstanding
A63: CASH FLOW STATEMENT
A64: Net income | B64: =B22 -> 1748 | C64: Calculated
A65: Depreciation and amortization | B65: =B28 -> 738 | C65: Calculated
A66: Stock-based compensation | B66: =B30 -> 1955 | C66: Calculated
A67: Other adjustments and working capital (residual) | B67: =B68-B64-B65-B66 -> 1003 | C67: Calculated
A68: Net cash from operating activities | B68: 5444 | C68: NetCashProvidedByUsedInOperatingActivities
A69: Capital expenditures | B69: -868 | C69: PaymentsToAcquirePropertyPlantAndEquipment
A70: Other investing activities (residual) | B70: =B71-B69 -> -821 | C70: Calculated
A71: Net cash from investing activities | B71: -1689 | C71: NetCashProvidedByUsedInInvestingActivities
A72: Repurchases of common stock | B72: -1840 | C72: PaymentsForRepurchaseOfCommonStock
A73: Dividends paid | C73: Not reported under a standard tag
A74: Other financing activities (residual) | B74: =B75-B72-B73 -> -500 | C74: Calculated
A75: Net cash from financing activities | B75: -2340 | C75: NetCashProvidedByUsedInFinancingActivities
A76: Effect of exchange rates on cash | B76: 7 | C76: EffectOfExchangeRateOnCashCashEquivalentsRestrictedCashAndRestrictedCashEquivalents
A77: Net change in cash | B77: =B68+B71+B75+B76 -> 1422 | C77: Calculated
A78: Memo
A79: Free cash flow (operating cash flow - capex) | B79: =B68+B69 -> 4576 | C79: Calculated
