Workbook

Sheet Ratios
A1: Profitability ratios: Amazon against US technology comparables
A2: Fiscal year 2025. All ratios are formulas on the Inputs sheet.
A4: Company | B4: Ticker | C4: Role | D4: Fiscal year end | E4: Gross margin | F4: Operating margin | G4: ROA | H4: ROE
A5: =Inputs!A5 -> Amazon | B5: =Inputs!B5 -> AMZN | C5: =Inputs!C5 -> Tested party | D5: =Inputs!D5 -> 46022 | E5: =IF(ISNUMBER(Inputs!G5),Inputs!G5/Inputs!E5,"n/a") -> 0.50285665 | F5: =Inputs!H5/Inputs!E5 -> 0.11155297 | G5: =Inputs!I5/Inputs!J5 -> 0.094946225 | H5: =Inputs!I5/Inputs!K5 -> 0.18894822
A6: =Inputs!A6 -> Microsoft | B6: =Inputs!B6 -> MSFT | C6: =Inputs!C6 -> Comparable | D6: =Inputs!D6 -> 45838 | E6: =IF(ISNUMBER(Inputs!G6),Inputs!G6/Inputs!E6,"n/a") -> 0.68823742 | F6: =Inputs!H6/Inputs!E6 -> 0.45621956 | G6: =Inputs!I6/Inputs!J6 -> 0.1645097 | H6: =Inputs!I6/Inputs!K6 -> 0.29647227
A7: =Inputs!A7 -> Nvidia | B7: =Inputs!B7 -> NVDA | C7: =Inputs!C7 -> Comparable | D7: =Inputs!D7 -> 46047 | E7: =IF(ISNUMBER(Inputs!G7),Inputs!G7/Inputs!E7,"n/a") -> 0.71068084 | F7: =Inputs!H7/Inputs!E7 -> 0.60381684 | G7: =Inputs!I7/Inputs!J7 -> 0.58058636 | H7: =Inputs!I7/Inputs!K7 -> 0.7633334
A8: =Inputs!A8 -> Alphabet | B8: =Inputs!B8 -> GOOGL | C8: =Inputs!C8 -> Comparable | D8: =Inputs!D8 -> 46022 | E8: =IF(ISNUMBER(Inputs!G8),Inputs!G8/Inputs!E8,"n/a") -> 0.59652315 | F8: =Inputs!H8/Inputs!E8 -> 0.32032639 | G8: =Inputs!I8/Inputs!J8 -> 0.2220296 | H8: =Inputs!I8/Inputs!K8 -> 0.31827869
A9: =Inputs!A9 -> Meta Platforms | B9: =Inputs!B9 -> META | C9: =Inputs!C9 -> Comparable | D9: =Inputs!D9 -> 46022 | E9: =IF(ISNUMBER(Inputs!G9),Inputs!G9/Inputs!E9,"n/a") -> 0.81999443 | F9: =Inputs!H9/Inputs!E9 -> 0.41437855 | G9: =Inputs!I9/Inputs!J9 -> 0.16517632 | H9: =Inputs!I9/Inputs!K9 -> 0.27829665
A10: =Inputs!A10 -> Apple | B10: =Inputs!B10 -> AAPL | C10: =Inputs!C10 -> Comparable | D10: =Inputs!D10 -> 45927 | E10: =IF(ISNUMBER(Inputs!G10),Inputs!G10/Inputs!E10,"n/a") -> 0.46905164 | F10: =Inputs!H10/Inputs!E10 -> 0.319708 | G10: =Inputs!I10/Inputs!J10 -> 0.31179626 | H10: =Inputs!I10/Inputs!K10 -> 1.5191298
A11: =Inputs!A11 -> Broadcom | B11: =Inputs!B11 -> AVGO | C11: =Inputs!C11 -> Comparable | D11: =Inputs!D11 -> 45963 | E11: =IF(ISNUMBER(Inputs!G11),Inputs!G11/Inputs!E11,"n/a") -> 0.67766525 | F11: =Inputs!H11/Inputs!E11 -> 0.39889179 | G11: =Inputs!I11/Inputs!J11 -> 0.13516704 | H11: =Inputs!I11/Inputs!K11 -> 0.28448064
A12: =Inputs!A12 -> ServiceNow | B12: =Inputs!B12 -> NOW | C12: =Inputs!C12 -> Comparable | D12: =Inputs!D12 -> 46022 | E12: =IF(ISNUMBER(Inputs!G12),Inputs!G12/Inputs!E12,"n/a") -> 0.77534267 | F12: =Inputs!H12/Inputs!E12 -> 0.13737009 | G12: =Inputs!I12/Inputs!J12 -> 0.067132652 | H12: =Inputs!I12/Inputs!K12 -> 0.13483493
A14: Comparable set (7 companies, Amazon excluded)
A15: Minimum | E15: =MIN(E6:E12) -> 0.46905164 | F15: =MIN(F6:F12) -> 0.13737009 | G15: =MIN(G6:G12) -> 0.067132652 | H15: =MIN(H6:H12) -> 0.13483493
A16: Lower quartile | E16: =QUARTILE(E6:E12,1) -> 0.6370942 | F16: =QUARTILE(F6:F12,1) -> 0.32001719 | G16: =QUARTILE(G6:G12,1) -> 0.14983837 | H16: =QUARTILE(H6:H12,1) -> 0.28138865
A17: Median | E17: =MEDIAN(E6:E12) -> 0.68823742 | F17: =MEDIAN(F6:F12) -> 0.39889179 | G17: =MEDIAN(G6:G12) -> 0.16517632 | H17: =MEDIAN(H6:H12) -> 0.29647227
A18: Upper quartile | E18: =QUARTILE(E6:E12,3) -> 0.74301176 | F18: =QUARTILE(F6:F12,3) -> 0.43529906 | G18: =QUARTILE(G6:G12,3) -> 0.26691293 | H18: =QUARTILE(H6:H12,3) -> 0.54080604
A19: Maximum | E19: =MAX(E6:E12) -> 0.81999443 | F19: =MAX(F6:F12) -> 0.60381684 | G19: =MAX(G6:G12) -> 0.58058636 | H19: =MAX(H6:H12) -> 1.5191298
A20: Average | E20: =AVERAGE(E6:E12) -> 0.67678506 | F20: =AVERAGE(F6:F12) -> 0.37867303 | G20: =AVERAGE(G6:G12) -> 0.2351997 | H20: =AVERAGE(H6:H12) -> 0.51354663
A22: Amazon against the comparable set
A23: Amazon | E23: =E5 -> 0.50285665 | F23: =F5 -> 0.11155297 | G23: =G5 -> 0.094946225 | H23: =H5 -> 0.18894822
A24: Difference from the median (percentage points) | E24: =(E5-E17)*100 -> -18.538078 | F24: =(F5-F17)*100 -> -28.733883 | G24: =(G5-G17)*100 -> -7.023009 | H24: =(H5-H17)*100 -> -10.752405
A25: Position against the interquartile range | E25: =IF(E5<E16,"Below",IF(E5>E18,"Above","Within")) -> Below | F25: =IF(F5<F16,"Below",IF(F5>F18,"Above","Within")) -> Below | G25: =IF(G5<G16,"Below",IF(G5>G18,"Above","Within")) -> Below | H25: =IF(H5<H16,"Below",IF(H5>H18,"Above","Within")) -> Below

Sheet Inputs
A1: Inputs: fiscal year 2025, USD millions
A2: Blue figures are reported values from each company's Form 10-K. Gross profit is a formula where the company does not report it.
A4: Company | B4: Ticker | C4: Role | D4: Fiscal year end | E4: Revenue | F4: Cost of revenue | G4: Gross profit | H4: Operating income | I4: Net income | J4: Total assets | K4: Total equity
A5: Amazon | B5: AMZN | C5: Tested party | D5: 46022 | E5: 716924 | F5: 356414 | G5: =E5-F5 -> 360510 | H5: 79975 | I5: 77670 | J5: 818042 | K5: 411065
A6: Microsoft | B6: MSFT | C6: Comparable | D6: 45838 | E6: 281724 | F6: 87831 | G6: 193893 | H6: 128528 | I6: 101832 | J6: 619003 | K6: 343479
A7: Nvidia | B7: NVDA | C7: Comparable | D7: 46047 | E7: 215938 | F7: 62475 | G7: 153463 | H7: 130387 | I7: 120067 | J7: 206803 | K7: 157293
A8: Alphabet | B8: GOOGL | C8: Comparable | D8: 46022 | E8: 402836 | F8: 162535 | G8: =E8-F8 -> 240301 | H8: 129039 | I8: 132170 | J8: 595281 | K8: 415265
A9: Meta Platforms | B9: META | C9: Comparable | D9: 46022 | E9: 200966 | F9: 36175 | G9: =E9-F9 -> 164791 | H9: 83276 | I9: 60458 | J9: 366021 | K9: 217243
A10: Apple | B10: AAPL | C10: Comparable | D10: 45927 | E10: 416161 | F10: 220960 | G10: 195201 | H10: 133050 | I10: 112010 | J10: 359241 | K10: 73733
A11: Broadcom | B11: AVGO | C11: Comparable | D11: 45963 | E11: 63887 | F11: 20593 | G11: 43294 | H11: 25484 | I11: 23126 | J11: 171092 | K11: 81292
A12: ServiceNow | B12: NOW | C12: Comparable | D12: 46022 | E12: 13278 | F12: 2983 | G12: 10295 | H12: 1824 | I12: 1748 | J12: 26038 | K12: 12964

Sheet Notes
A1: Notes
A2: Definitions
A3: Gross margin = gross profit / revenue.
A4: Operating margin = operating income / revenue.
A5: ROA (return on assets) = net income / total assets at fiscal year end.
A6: ROE (return on equity) = net income / total stockholders' equity at fiscal year end.
A8: Points to keep in mind
A9: ROA and ROE use year-end balances, not the average of opening and closing balances, because the analysis uses 2025 figures only.
A10: Fiscal years differ. Each company's own fiscal year 2025 is used; the dates are shown next to each company.
A11: Nvidia: the year ended 25 January 2026 is used because it covers 11 months of calendar 2025.
A12: Amazon does not report gross profit. It is calculated here as revenue less cost of sales.
A13: Apple has small equity relative to earnings because of share buybacks, which makes its ROE very high.
... A19: Retrieved on 2026-10-13.
